tests/__init__.py
tests/test_relevance_analyzer.py
tests/test_subtheme_analyzer.py
textscope/__init__.py
textscope/config.py
textscope/config_loader.py
textscope/relevance_analyzer.py
textscope/subtheme_analyzer.py
textscope/data/config.yaml
textscope-0.1.7.dist-info/LICENSE
textscope-0.1.7.dist-info/METADATA
textscope-0.1.7.dist-info/WHEEL
textscope-0.1.7.dist-info/top_level.txt
textscope-0.1.7.dist-info/RECORD
