Metadata-Version: 2.1
Name: textscope
Version: 0.1.7
Summary: A Python text analysis library for relevance and subtheme detection
Home-page: UNKNOWN
Author: Marcos Fernández-Pichel
Author-email: marcosfernandez.pichel@usc.es
License: UNKNOWN
Platform: UNKNOWN
License-File: LICENSE
Requires-Dist: nltk
Requires-Dist: numpy
Requires-Dist: pytest
Requires-Dist: pyyaml
Requires-Dist: torch
Requires-Dist: transformers
